<?xml version="1.0" encoding="utf-8" ?>
<dwsync>
<file name="1x1.png" server="81.16.141.210" local="132024266112047675" remote="131552532000000000" Dst="0" />
<file name="bottom_line.png" server="81.16.141.210" local="132024266113886426" remote="131552532000000000" Dst="0" />
<file name="1.jpg" server="81.16.141.210" local="132024266114276443" remote="131552532000000000" Dst="0" />
<file name="bg_new.jpg" server="81.16.141.210" local="132024266115305602" remote="131552532000000000" Dst="0" />
<file name="combatz_logo.png" server="81.16.141.210" local="132024266116354986" remote="131552532000000000" Dst="0" />
<file name="healvortex.gif" server="81.16.141.210" local="132024266123702228" remote="131552532000000000" Dst="0" />
<file name="leftd.png" server="81.16.141.210" local="132024266126440673" remote="131552532000000000" Dst="0" />
<file name="leftl.png" server="81.16.141.210" local="132024266126440673" remote="131552532000000000" Dst="0" />
<file name="left.png" server="81.16.141.210" local="132024266126630557" remote="131552532000000000" Dst="0" />
<file name="manavortex.gif" server="81.16.141.210" local="132024266128999358" remote="131552532000000000" Dst="0" />
<file name="pri_radio.png" server="81.16.141.210" local="132024266128999358" remote="131552532000000000" Dst="0" />
<file name="psi_btn1.png" server="81.16.141.210" local="132024266129239072" remote="131552532000000000" Dst="0" />
<file name="reg_txt1.png" server="81.16.141.210" local="132024266131527786" remote="131552532000000000" Dst="0" />
<file name="psi_checkbox.png" server="81.16.141.210" local="132024266131937545" remote="131552532000000000" Dst="0" />
<file name="reg_bg.png" server="81.16.141.210" local="132024266131937545" remote="131552532000000000" Dst="0" />
<file name="reg_txt2.png" server="81.16.141.210" local="132024266134835883" remote="131552532000000000" Dst="0" />
<file name="rightl.png" server="81.16.141.210" local="132024266134845879" remote="131552532000000000" Dst="0" />
<file name="rightd.png" server="81.16.141.210" local="132024266135035769" remote="131552532000000000" Dst="0" />
<file name="right.png" server="81.16.141.210" local="132024266137254504" remote="131552532000000000" Dst="0" />
<file name="top_line.png" server="81.16.141.210" local="132024266171834800" remote="131552532000000000" Dst="0" />
</dwsync>